jamegresc.py
jamegresc-0.1.9.dist-info/METADATA
jamegresc-0.1.9.dist-info/WHEEL
jamegresc-0.1.9.dist-info/entry_points.txt
jamegresc-0.1.9.dist-info/top_level.txt
jamegresc-0.1.9.dist-info/RECORD
