Metadata-Version: 2.1
Name: jamegresc
Version: 0.1.9
Summary: A package for visualization of Resource recovery amount and gain on sale data in Meguro
Home-page: https://github.com/TakahitoAsakawa/jamegresc
Author: takahito asakawa
Author-email: s2022051@gmail.com
License: UNKNOWN
Project-URL: Bug Tracker, https://github.com/TakahitoAsakawa/jamegresc
Platform: UNKNOWN
Classifier: Programming Language :: Python :: 3
Classifier: License :: OSI Approved :: MIT License
Classifier: Operating System :: OS Independent
Requires-Python: >=3.7.7
